psa_prizes/__init__.py
psa_prizes/analyze.py
psa_prizes/main.py
psa_prizes/scrape.py
psa_prizes-0.1.2.dist-info/entry_points.txt
psa_prizes-0.1.2.dist-info/LICENSE
psa_prizes-0.1.2.dist-info/WHEEL
psa_prizes-0.1.2.dist-info/METADATA
psa_prizes-0.1.2.dist-info/RECORD
