Metadata-Version: 2.1
Name: psa-prizes
Version: 0.1.2
Summary: The PSA prizes project.
Home-page: https://github.com/tostenzel/psa-prizes
License: MIT
Keywords: trading cards,grading,PSA,prizes,ebay
Author: Tobias Stenzel
Author-email: tobias.stenzel@mailbox.org
Requires-Python: >=3.7,<4.0
Classifier: License :: OSI Approved :: MIT License
Classifier: Programming Language :: Python :: 3
Classifier: Programming Language :: Python :: 3.7
Classifier: Programming Language :: Python :: 3.8
Requires-Dist: IPython (>=7.15.0,<8.0.0)
Requires-Dist: beautifulsoup4 (>=4.9.1,<5.0.0)
Requires-Dist: html5lib (>=1.0.1,<2.0.0)
Requires-Dist: matplotlib (>=3.2.1,<4.0.0)
Requires-Dist: pandas (>=1.0.4,<2.0.0)
Requires-Dist: requests (>=2.23.0,<3.0.0)
Project-URL: Documentation, https://psa-prizes.readthedocs.io
Project-URL: Repository, https://github.com/tostenzel/psa-prizes
